goto/__init__.py
goto/goto.py
goto_module-1.1.0.dist-info/METADATA
goto_module-1.1.0.dist-info/WHEEL
goto_module-1.1.0.dist-info/top_level.txt
goto_module-1.1.0.dist-info/RECORD
