Metadata-Version: 2.1
Name: goto-module
Version: 1.1.0
Summary: Goto module
Home-page: UNKNOWN
Author: Meet Patel
Author-email: <meetp6116@gmail.com>
License: UNKNOWN
Keywords: python,goto package,goto,goto-module,goto module
Platform: UNKNOWN
Classifier: Development Status :: 3 - Alpha
Classifier: Intended Audience :: Education
Classifier: Programming Language :: Python :: 2
Classifier: Programming Language :: Python :: 3
Classifier: Operating System :: MacOS :: MacOS X
Classifier: Operating System :: Microsoft :: Windows
